bdd100k/__init__.py
bdd100k/py.typed
bdd100k/common/__init__.py
bdd100k/common/bitmask.py
bdd100k/common/logger.py
bdd100k/common/typing.py
bdd100k/common/utils.py
bdd100k/configs/box_track.toml
bdd100k/configs/det.toml
bdd100k/configs/drivable.toml
bdd100k/configs/ins_seg.toml
bdd100k/configs/lane_mark.toml
bdd100k/configs/pan_seg.toml
bdd100k/configs/pose.toml
bdd100k/configs/seg_track.toml
bdd100k/configs/sem_seg.toml
bdd100k/data/__init__.py
bdd100k/data/gen_lists.py
bdd100k/data/parallel.py
bdd100k/eval/__init__.py
bdd100k/eval/ins_seg.py
bdd100k/eval/lane.py
bdd100k/eval/mots.py
bdd100k/eval/pan_seg.py
bdd100k/eval/run.py
bdd100k/eval/seg.py
bdd100k/label/__init__.py
bdd100k/label/from_coco.py
bdd100k/label/from_coco_panseg.py
bdd100k/label/label.py
bdd100k/label/palette.py
bdd100k/label/to_coco.py
bdd100k/label/to_coco_panseg.py
bdd100k/label/to_color.py
bdd100k/label/to_mask.py
bdd100k/label/to_rle.py
bdd100k/label/to_scalabel.py
bdd100k/vis/__init__.py
bdd100k/vis/geometry.py
bdd100k/vis/trajectory.py
bdd100k/vis/viewer.py
bdd100k-1.0.1.dist-info/LICENSE
bdd100k-1.0.1.dist-info/METADATA
bdd100k-1.0.1.dist-info/WHEEL
bdd100k-1.0.1.dist-info/top_level.txt
bdd100k-1.0.1.dist-info/RECORD
