Metadata-Version: 2.1
Name: bdd100k
Version: 1.0.1
Summary: BDD100K Dataset Toolkit
Home-page: https://www.bdd100k.com/
Author: Fisher Yu
Author-email: i@yf.io
Project-URL: Documentation, https://doc.bdd100k.com/
Project-URL: Source, https://github.com/bdd100k/bdd100k
Project-URL: Tracker, https://github.com/bdd100k/bdd100k/issues
Classifier: Programming Language :: Python :: 3
Classifier: License :: OSI Approved :: BSD License
Classifier: Operating System :: OS Independent
Requires-Python: >=3.7
License-File: LICENSE
Requires-Dist: gmplot
Requires-Dist: joblib
Requires-Dist: matplotlib
Requires-Dist: motmetrics
Requires-Dist: numpy
Requires-Dist: pandas
Requires-Dist: pillow
Requires-Dist: pycocotools
Requires-Dist: scalabel
Requires-Dist: scikit-image
Requires-Dist: toml
Requires-Dist: tqdm
Requires-Dist: tabulate
